backend/__init__.py
backend/api/__init__.py
backend/api/v1/__init__.py
backend/application/__init__.py
backend/core/__init__.py
backend/domain/__init__.py
backend/infrastructure/__init__.py
backend/infrastructure/database.py
backend/infrastructure/orm/__init__.py
backend/main.py
trainer_loop-0.1.0.dist-info/LICENSE
trainer_loop-0.1.0.dist-info/METADATA
trainer_loop-0.1.0.dist-info/WHEEL
trainer_loop-0.1.0.dist-info/entry_points.txt
trainer_loop-0.1.0.dist-info/RECORD
