Metadata-Version: 2.1
Name: traiNER-loop
Version: 0.1.0
Summary: An application for data annotation assisted by a model (human in the loop)
Author: iokninsk
Author-email: irekokninski12370@gmail.com
Requires-Python: >=3.11,<4.0
Classifier: Development Status :: 1 - Planning
Classifier: Programming Language :: Python :: 3
Classifier: Programming Language :: Python :: 3.11
Classifier: Programming Language :: Python :: 3.12
Requires-Dist: fastapi (>=0.111.0,<0.112.0)
